RsCMPX_NrFr2Meas/RsCMPX_NrFr2Meas.py
RsCMPX_NrFr2Meas/__init__.py
RsCMPX_NrFr2Meas/enums.py
RsCMPX_NrFr2Meas/repcap.py
RsCMPX_NrFr2Meas/CustomFiles/__init__.py
RsCMPX_NrFr2Meas/CustomFiles/events.py
RsCMPX_NrFr2Meas/CustomFiles/reliability.py
RsCMPX_NrFr2Meas/CustomFiles/utilities.py
RsCMPX_NrFr2Meas/Implementations/__init__.py
RsCMPX_NrFr2Meas/Implementations/Configure/__init__.py
RsCMPX_NrFr2Meas/Implementations/Configure/NrMmwMeas/Network.py
RsCMPX_NrFr2Meas/Implementations/Configure/NrMmwMeas/Susage.py
RsCMPX_NrFr2Meas/Implementations/Configure/NrMmwMeas/__init__.py
RsCMPX_NrFr2Meas/Implementations/Configure/NrMmwMeas/Caggregation/AcSpacing.py
RsCMPX_NrFr2Meas/Implementations/Configure/NrMmwMeas/Caggregation/Cbandwidth.py
RsCMPX_NrFr2Meas/Implementations/Configure/NrMmwMeas/Caggregation/NgBandwidth.py
RsCMPX_NrFr2Meas/Implementations/Configure/NrMmwMeas/Caggregation/__init__.py
RsCMPX_NrFr2Meas/Implementations/Configure/NrMmwMeas/Caggregation/Frequency/Aggregated.py
RsCMPX_NrFr2Meas/Implementations/Configure/NrMmwMeas/Caggregation/Frequency/__init__.py
RsCMPX_NrFr2Meas/Implementations/Configure/NrMmwMeas/Cc/Cbandwidth.py
RsCMPX_NrFr2Meas/Implementations/Configure/NrMmwMeas/Cc/Frequency.py
RsCMPX_NrFr2Meas/Implementations/Configure/NrMmwMeas/Cc/Nallocations.py
RsCMPX_NrFr2Meas/Implementations/Configure/NrMmwMeas/Cc/NbwParts.py
RsCMPX_NrFr2Meas/Implementations/Configure/NrMmwMeas/Cc/PlcId.py
RsCMPX_NrFr2Meas/Implementations/Configure/NrMmwMeas/Cc/TaPosition.py
RsCMPX_NrFr2Meas/Implementations/Configure/NrMmwMeas/Cc/__init__.py
RsCMPX_NrFr2Meas/Implementations/Configure/NrMmwMeas/Cc/Allocation/Bwp.py
RsCMPX_NrFr2Meas/Implementations/Configure/NrMmwMeas/Cc/Allocation/Ctype.py
RsCMPX_NrFr2Meas/Implementations/Configure/NrMmwMeas/Cc/Allocation/__init__.py
RsCMPX_NrFr2Meas/Implementations/Configure/NrMmwMeas/Cc/Allocation/Pucch/Enable.py
RsCMPX_NrFr2Meas/Implementations/Configure/NrMmwMeas/Cc/Allocation/Pucch/IcShift.py
RsCMPX_NrFr2Meas-5.0.90.dist-info/METADATA
RsCMPX_NrFr2Meas-5.0.90.dist-info/WHEEL
RsCMPX_NrFr2Meas-5.0.90.dist-info/top_level.txt
RsCMPX_NrFr2Meas-5.0.90.dist-info/RECORD
